DagVisitor/__init__.py
DagVisitor/_visitor.py
DagVisitor/visitor.py
DagVisitor-1.0.1.dist-info/LICENSE
DagVisitor-1.0.1.dist-info/METADATA
DagVisitor-1.0.1.dist-info/WHEEL
DagVisitor-1.0.1.dist-info/top_level.txt
DagVisitor-1.0.1.dist-info/RECORD
